[
  {
    "OST": "Canciones de Artifyber",
    "image": "",
    "image_alt": "",
    "hasRemix": false
  },
  {
    "OST": "Canciones de Femtanyl",
    "image": "",
    "image_alt": "",
    "hasRemix": false
  },
  {
    "OST": "Canciones de Yonkagor",
    "image": "",
    "image_alt": "",
    "hasRemix": false
  },
  {
    "OST": "Canciones de Narpy",
    "image": "",
    "image_alt": "",
    "hasRemix": false
  },
  {
    "OST": "Canciones de Snuffles",
    "image": "",
    "image_alt": "",
    "hasRemix": false
  },
  {
    "OST": "Canciones de Ivycomb",
    "image": "",
    "image_alt": "",
    "hasRemix": false
  },
  {
    "OST": "Canciones de Whsprs",
    "image": "",
    "image_alt": "",
    "hasRemix": false
  },
  {
    "OST": "Canciones de Kennyoung",
    "image": "",
    "image_alt": "",
    "hasRemix": false
  },
  {
    "OST": "Canciones de Frizk",
    "image": "",
    "image_alt": "",
    "hasRemix": false
  },
  {
    "OST": "Canciones de Betu",
    "image": "",
    "image_alt": "",
    "hasRemix": false
  },
  {
    "OST": "Canciones de Silva Hound",
    "image": "",
    "image_alt": "",
    "hasRemix": false
  },
  {
    "OST": "Canciones de VRCVictory",
    "image": "",
    "image_alt": "",
    "hasRemix": false
  },
  {
    "OST": "Canciones de Lizzy",
    "image": "",
    "image_alt": "",
    "hasRemix": false
  },
  {
    "OST": "Canciones de Lianhua",
    "image": "",
    "image_alt": "",
    "hasRemix": false
  },
  {
    "OST": "Canciones de Metaroom",
    "image": "",
    "image_alt": "",
    "hasRemix": false
  }
]
